{"skeleton":{"hash":"4O19jCYPfoHDSBuOBkwOdLl6OtY","spine":"3.6.53","width":1747.76,"height":1080,"images":""},"bones":[{"name":"root"},{"name":"effect","parent":"root","length":16,"scaleX":0.75,"scaleY":0.75},{"name":"effect2","parent":"effect","length":15.35,"x":161.07,"y":-399.12},{"name":"effect3","parent":"effect","length":15.35,"x":193.18,"y":-457.12,"scaleX":0.761,"scaleY":0.761},{"name":"effect4","parent":"effect","length":15.35,"x":257.87,"y":-431.53,"scaleX":0.65,"scaleY":0.65},{"name":"effect5","parent":"effect","length":15.35,"rotation":180,"x":-215.35,"y":-428.76,"scaleX":0.819,"scaleY":0.819},{"name":"effect6","parent":"effect","length":15.35,"rotation":180,"x":-299.7,"y":-404.89,"scaleX":0.761,"scaleY":0.761},{"name":"effect7","parent":"effect","length":15.35,"rotation":180,"x":-270.71,"y":-455.24,"scaleX":0.65,"scaleY":0.65},{"name":"fang1","parent":"effect2","length":34.01,"x":7.82,"y":-3.5},{"name":"fang2","parent":"effect2","length":34.01,"x":7.82,"y":-3.5},{"name":"fang3","parent":"effect3","length":34.01,"x":7.82,"y":-3.5},{"name":"fang4","parent":"effect3","length":34.01,"x":7.82,"y":-3.5},{"name":"fang5","parent":"effect4","length":34.01,"x":7.82,"y":-3.5},{"name":"fang6","parent":"effect4","length":34.01,"x":7.82,"y":-3.5},{"name":"fang7","parent":"effect5","length":34.01,"x":7.82,"y":-3.5},{"name":"fang8","parent":"effect5","length":34.01,"x":7.82,"y":-3.5},{"name":"fang9","parent":"effect6","length":34.01,"x":7.82,"y":-3.5},{"name":"fang10","parent":"effect6","length":34.01,"x":7.82,"y":-3.5},{"name":"fang11","parent":"effect7","length":34.01,"x":7.82,"y":-3.5},{"name":"fang12","parent":"effect7","length":34.01,"x":7.82,"y":-3.5},{"name":"haoli","parent":"effect","length":34.01,"x":-353.5,"y":267.39},{"name":"huozeng1","parent":"effect","length":34.01,"x":-104.24,"y":-203.94},{"name":"liji","parent":"effect","length":34.01,"x":-40.79,"y":-426.01},{"name":"light01","parent":"liji","length":72.51,"x":40.79,"y":56.65},{"name":"light1","parent":"liji","length":72.51,"x":40.79,"y":-52.12},{"name":"liji2","parent":"liji","length":34.01,"x":18.13,"y":-4.53},{"name":"liwuhe","parent":"effect","length":34.01,"x":-6.8,"y":-512.12,"scaleX":4,"scaleY":4},{"name":"ren","parent":"effect","length":34.01,"x":759.54,"scaleX":2,"scaleY":2}],"slots":[{"name":"dadiban","bone":"liwuhe","attachment":"dadiban"},{"name":"anniu","bone":"liji","attachment":"anniu"},{"name":"lijizhuce","bone":"liji2","attachment":"lijizhuce"},{"name":"diban","bone":"huozeng1","attachment":"diban"},{"name":"zhucesonghaoli","bone":"haoli","attachment":"zhucesonghaoli"},{"name":"meinv","bone":"ren","attachment":"meinv"},{"name":"guang02","bone":"light01","attachment":"guang02","blend":"additive"},{"name":"guang2","bone":"light1","attachment":"guang02","blend":"additive"},{"name":"fang","bone":"fang1","attachment":"fang","blend":"additive"},{"name":"fang7","bone":"fang7","attachment":"fang","blend":"additive"},{"name":"fang3","bone":"fang3","attachment":"fang","blend":"additive"},{"name":"fang9","bone":"fang9","attachment":"fang","blend":"additive"},{"name":"fang5","bone":"fang5","attachment":"fang","blend":"additive"},{"name":"fang11","bone":"fang11","attachment":"fang","blend":"additive"},{"name":"fang2","bone":"fang2","attachment":"fang","blend":"additive"},{"name":"fang8","bone":"fang8","attachment":"fang","blend":"additive"},{"name":"fang4","bone":"fang4","attachment":"fang","blend":"additive"},{"name":"fang10","bone":"fang10","attachment":"fang","blend":"additive"},{"name":"fang6","bone":"fang6","attachment":"fang","blend":"additive"},{"name":"fang12","bone":"fang12","attachment":"fang","blend":"additive"}],"skins":{"default":{"anniu":{"anniu":{"width":713,"height":116}},"dadiban":{"dadiban":{"y":133.13,"width":491,"height":274}},"diban":{"diban":{"scaleX":2,"scaleY":2,"width":613,"height":144}},"fang":{"fang":{"width":25,"height":23}},"fang10":{"fang":{"width":25,"height":23}},"fang11":{"fang":{"width":25,"height":23}},"fang12":{"fang":{"width":25,"height":23}},"fang2":{"fang":{"width":25,"height":23}},"fang3":{"fang":{"width":25,"height":23}},"fang4":{"fang":{"width":25,"height":23}},"fang5":{"fang":{"width":25,"height":23}},"fang6":{"fang":{"width":25,"height":23}},"fang7":{"fang":{"width":25,"height":23}},"fang8":{"fang":{"width":25,"height":23}},"fang9":{"fang":{"width":25,"height":23}},"guang02":{"guang02":{"width":739,"height":147}},"guang2":{"guang02":{"width":739,"height":147}},"lijizhuce":{"lijizhuce":{"width":275,"height":61}},"meinv":{"meinv":{"width":582,"height":720}},"zhucesonghaoli":{"zhucesonghaoli":{"scaleX":2,"scaleY":2,"width":317,"height":78}}}},"animations":{"animation1":{"slots":{"anniu":{"color":[{"time":0,"color":"ffffff00","curve":"stepped"},{"time":0.2667,"color":"ffffff00"},{"time":0.4333,"color":"ffffffff"}]},"dadiban":{"color":[{"time":0,"color":"ffffff00"},{"time":0.1667,"color":"ffffffff"}],"attachment":[{"time":0,"name":"dadiban"}]},"diban":{"color":[{"time":0,"color":"ffffff00","curve":"stepped"},{"time":0.2333,"color":"ffffff00"},{"time":0.4333,"color":"ffffffff"}]},"guang02":{"color":[{"time":0,"color":"ffffff00","curve":"stepped"},{"time":0.3,"color":"ffffff00"},{"time":0.4667,"color":"ffffffff"}]},"guang2":{"color":[{"time":0,"color":"ffffff00","curve":"stepped"},{"time":0.3,"color":"ffffff00"},{"time":0.4667,"color":"ffffffff"}]},"lijizhuce":{"color":[{"time":0,"color":"ffffff00","curve":"stepped"},{"time":0.3,"color":"ffffff00"},{"time":0.4667,"color":"ffffffff"}]},"meinv":{"color":[{"time":0,"color":"ffffff00"},{"time":0.1667,"color":"ffffffff"}]},"zhucesonghaoli":{"color":[{"time":0,"color":"ffffff00","curve":"stepped"},{"time":0.2333,"color":"ffffff00"},{"time":0.3333,"color":"ffffffff"}]}},"bones":{"liwuhe":{"scale":[{"time":0,"x":0,"y":0},{"time":0.1667,"x":1.075,"y":1.075},{"time":0.2333,"x":0.975,"y":0.975},{"time":0.3333,"x":1,"y":1}]},"ren":{"translate":[{"time":0,"x":826.96,"y":0,"curve":[0.25,0,0.75,1]},{"time":0.1667,"x":-61.62,"y":0,"curve":[0.25,0,0.75,1]},{"time":0.2667,"x":0,"y":0}]},"haoli":{"scale":[{"time":0.2333,"x":2.204,"y":2.204},{"time":0.3333,"x":0.8,"y":0.8},{"time":0.4667,"x":1,"y":1}]},"liji":{"translate":[{"time":0.2667,"x":-966.41,"y":0,"curve":[0.25,0,0.75,1]},{"time":0.4333,"x":55.13,"y":0,"curve":[0.25,0,0.75,1]},{"time":0.5333,"x":0,"y":0}]}},"drawOrder":[{"time":0}]},"animation2":{"slots":{"fang":{"color":[{"time":0,"color":"ffffff00"},{"time":0.8333,"color":"ffffffff"},{"time":1.6667,"color":"ffffff00"}]},"fang2":{"color":[{"time":0,"color":"ffffffff"},{"time":0.8333,"color":"ffffff00","curve":"stepped"},{"time":0.8667,"color":"ffffff00"},{"time":1.6667,"color":"ffffffff"}]},"fang3":{"color":[{"time":0,"color":"ffffff00"},{"time":0.8333,"color":"ffffffff"},{"time":1.6667,"color":"ffffff00"}]},"fang4":{"color":[{"time":0,"color":"ffffffff"},{"time":0.8333,"color":"ffffff00","curve":"stepped"},{"time":0.8667,"color":"ffffff00"},{"time":1.6667,"color":"ffffffff"}]},"fang5":{"color":[{"time":0,"color":"ffffff00"},{"time":0.8333,"color":"ffffffff"},{"time":1.6667,"color":"ffffff00"}]},"fang6":{"color":[{"time":0,"color":"ffffffff"},{"time":0.8333,"color":"ffffff00","curve":"stepped"},{"time":0.8667,"color":"ffffff00"},{"time":1.6667,"color":"ffffffff"}]},"fang7":{"color":[{"time":0,"color":"ffffff00"},{"time":0.8333,"color":"ffffffff"},{"time":1.6667,"color":"ffffff00"}]},"fang8":{"color":[{"time":0,"color":"ffffffff"},{"time":0.8333,"color":"ffffff00","curve":"stepped"},{"time":0.8667,"color":"ffffff00"},{"time":1.6667,"color":"ffffffff"}]},"fang9":{"color":[{"time":0,"color":"ffffff00"},{"time":0.8333,"color":"ffffffff"},{"time":1.6667,"color":"ffffff00"}]},"fang10":{"color":[{"time":0,"color":"ffffffff"},{"time":0.8333,"color":"ffffff00","curve":"stepped"},{"time":0.8667,"color":"ffffff00"},{"time":1.6667,"color":"ffffffff"}]},"fang11":{"color":[{"time":0,"color":"ffffff00"},{"time":0.8333,"color":"ffffffff"},{"time":1.6667,"color":"ffffff00"}]},"fang12":{"color":[{"time":0,"color":"ffffffff"},{"time":0.8333,"color":"ffffff00","curve":"stepped"},{"time":0.8667,"color":"ffffff00"},{"time":1.6667,"color":"ffffffff"}]},"guang2":{"color":[{"time":0,"color":"ffffffff"},{"time":0.8333,"color":"ffffff00"},{"time":1.6667,"color":"ffffffff"}]},"guang02":{"color":[{"time":0,"color":"ffffffff"},{"time":0.8333,"color":"ffffff00"},{"time":1.6667,"color":"ffffffff"}]}},"bones":{"liji2":{"scale":[{"time":0,"x":1,"y":1,"curve":"stepped"},{"time":0.3333,"x":1,"y":1,"curve":[0.382,0.57,0.735,1]},{"time":0.5,"x":1.4,"y":1.4,"curve":[0.295,0,0.633,0.37]},{"time":0.6667,"x":0.9,"y":0.9,"curve":[0.298,0.21,0.644,0.59]},{"time":0.8333,"x":1,"y":1,"curve":"stepped"},{"time":1.6667,"x":1,"y":1}]},"fang1":{"translate":[{"time":0,"x":-18.77,"y":0},{"time":1.6667,"x":75.06,"y":0}]},"fang2":{"translate":[{"time":0,"x":-18.77,"y":0},{"time":0.8333,"x":28.15,"y":0},{"time":0.8667,"x":-65.64,"y":0},{"time":1.6667,"x":-18.77,"y":0}]},"fang3":{"translate":[{"time":0,"x":-18.77,"y":0},{"time":1.6667,"x":75.06,"y":0}]},"fang4":{"translate":[{"time":0,"x":-18.77,"y":0},{"time":0.8333,"x":28.15,"y":0},{"time":0.8667,"x":-65.64,"y":0},{"time":1.6667,"x":-18.77,"y":0}]},"fang5":{"translate":[{"time":0,"x":-18.77,"y":0},{"time":1.6667,"x":75.06,"y":0}]},"fang6":{"translate":[{"time":0,"x":-18.77,"y":0},{"time":0.8333,"x":28.15,"y":0},{"time":0.8667,"x":-65.64,"y":0},{"time":1.6667,"x":-18.77,"y":0}]},"fang7":{"translate":[{"time":0,"x":-18.77,"y":0},{"time":1.6667,"x":75.06,"y":0}]},"fang8":{"translate":[{"time":0,"x":-18.77,"y":0},{"time":0.8333,"x":28.15,"y":0},{"time":0.8667,"x":-65.64,"y":0},{"time":1.6667,"x":-18.77,"y":0}]},"fang9":{"translate":[{"time":0,"x":-18.77,"y":0},{"time":1.6667,"x":75.06,"y":0}]},"fang10":{"translate":[{"time":0,"x":-18.77,"y":0},{"time":0.8333,"x":28.15,"y":0},{"time":0.8667,"x":-65.64,"y":0},{"time":1.6667,"x":-18.77,"y":0}]},"fang11":{"translate":[{"time":0,"x":-18.77,"y":0},{"time":1.6667,"x":75.06,"y":0}]},"fang12":{"translate":[{"time":0,"x":-18.77,"y":0},{"time":0.8333,"x":28.15,"y":0},{"time":0.8667,"x":-65.64,"y":0},{"time":1.6667,"x":-18.77,"y":0}]}}}}}