{"skeleton":{"hash":"odd3f1k7qqEWjrdt06EiPjXefp0","spine":"3.6.53","width":324.96,"height":217.45,"images":""},"bones":[{"name":"root","scaleX":0.75,"scaleY":0.75},{"name":"che","parent":"root","x":9.1,"y":-4.39},{"name":"che2","parent":"che","length":29.17,"x":-9.1,"y":4.39},{"name":"bone2","parent":"che2","x":7.82,"y":11.93},{"name":"bone3","parent":"root","x":-70.11,"y":100.52},{"name":"bone4","parent":"root","x":-70.11,"y":100.52},{"name":"deng01","parent":"bone2","length":17.12,"x":-59.44,"y":11.92},{"name":"deng1","parent":"bone2","length":17.12,"x":-167.37,"y":24,"scaleX":0.616,"scaleY":0.616}],"slots":[{"name":"chouma4","bone":"bone3","attachment":"chouma"},{"name":"chouma5","bone":"bone4","attachment":"chouma","blend":"additive"},{"name":"xulie","bone":"bone2","attachment":"che/che_09"},{"name":"zi_di","bone":"root","attachment":"zi_di"},{"name":"zi","bone":"root","attachment":"zi"},{"name":"deng02_00","bone":"deng01","attachment":"deng02_00","blend":"additive"},{"name":"deng02_0","bone":"deng1","attachment":"deng02_00","blend":"additive"}],"skins":{"default":{"chouma4":{"chouma":{"x":-14.25,"y":-3.95,"width":73,"height":71}},"chouma5":{"chouma":{"x":-14.25,"y":-3.95,"width":73,"height":71}},"deng02_0":{"deng02_00":{"width":214,"height":131}},"deng02_00":{"deng02_00":{"width":214,"height":131}},"xulie":{"che/che_00":{"width":400,"height":286},"che/che_01":{"width":400,"height":286},"che/che_02":{"width":400,"height":286},"che/che_03":{"width":400,"height":286},"che/che_04":{"width":400,"height":286},"che/che_05":{"width":400,"height":286},"che/che_06":{"width":400,"height":286},"che/che_07":{"width":400,"height":286},"che/che_08":{"width":400,"height":286},"che/che_09":{"width":400,"height":286}},"zi":{"zi":{"y":-90,"width":264,"height":70}},"zi_di":{"zi_di":{"y":-88,"width":356,"height":94}}}},"animations":{"animation":{"slots":{"chouma4":{"attachment":[{"time":0,"name":"chouma"},{"time":0.9667,"name":"chouma"}]},"chouma5":{"color":[{"time":0,"color":"ffffff00"},{"time":0.5,"color":"ffffffb8"},{"time":0.9667,"color":"ffffff00"}],"attachment":[{"time":0,"name":"chouma"},{"time":0.9667,"name":"chouma"}]},"deng02_00":{"color":[{"time":0,"color":"ffffff00"},{"time":0.5,"color":"ffffffff"},{"time":0.9667,"color":"ffffff00"}],"attachment":[{"time":0,"name":"deng02_00"},{"time":0.9667,"name":"deng02_00"}]},"deng02_0":{"color":[{"time":0,"color":"ffffff00"},{"time":0.5,"color":"ffffffff"},{"time":0.9667,"color":"ffffff00"}],"attachment":[{"time":0,"name":"deng02_00"},{"time":0.9667,"name":"deng02_00"}]},"xulie":{"attachment":[{"time":0,"name":"che/che_00"},{"time":0.0333,"name":"che/che_01"},{"time":0.0667,"name":"che/che_02"},{"time":0.1,"name":"che/che_03"},{"time":0.1333,"name":"che/che_04"},{"time":0.1667,"name":"che/che_05"},{"time":0.2,"name":"che/che_06"},{"time":0.2333,"name":"che/che_07"},{"time":0.2667,"name":"che/che_08"},{"time":0.3,"name":"che/che_09"},{"time":0.3333,"name":"che/che_00"},{"time":0.3667,"name":"che/che_01"},{"time":0.4,"name":"che/che_02"},{"time":0.4333,"name":"che/che_03"},{"time":0.4667,"name":"che/che_04"},{"time":0.5,"name":"che/che_05"},{"time":0.5333,"name":"che/che_06"},{"time":0.5667,"name":"che/che_07"},{"time":0.6,"name":"che/che_08"},{"time":0.6333,"name":"che/che_09"},{"time":0.6667,"name":"che/che_00"},{"time":0.7,"name":"che/che_01"},{"time":0.7333,"name":"che/che_02"},{"time":0.7667,"name":"che/che_03"},{"time":0.8,"name":"che/che_04"},{"time":0.8333,"name":"che/che_05"},{"time":0.8667,"name":"che/che_06"},{"time":0.9,"name":"che/che_07"},{"time":0.9333,"name":"che/che_08"},{"time":0.9667,"name":"che/che_09"}]},"zi":{"attachment":[{"time":0,"name":"zi"},{"time":0.9667,"name":"zi"}]},"zi_di":{"attachment":[{"time":0,"name":"zi_di"},{"time":0.9667,"name":"zi_di"}]}},"bones":{"bone3":{"rotate":[{"time":0,"angle":0,"curve":[0.25,0,0.75,1]},{"time":0.5,"angle":-6.91,"curve":[0.25,0,0.75,1]},{"time":0.9667,"angle":0}],"scale":[{"time":0,"x":1,"y":1,"curve":[0.25,0,0.75,1]},{"time":0.5,"x":1.067,"y":1.067,"curve":[0.25,0,0.75,1]},{"time":0.9667,"x":1,"y":1}]},"bone4":{"rotate":[{"time":0,"angle":0,"curve":[0.25,0,0.75,1]},{"time":0.5,"angle":-6.91,"curve":[0.25,0,0.75,1]},{"time":0.9667,"angle":0}],"scale":[{"time":0,"x":1,"y":1,"curve":[0.25,0,0.75,1]},{"time":0.5,"x":1.067,"y":1.067,"curve":[0.25,0,0.75,1]},{"time":0.9667,"x":1.23,"y":1.23}]},"bone2":{"translate":[{"time":0,"x":0,"y":0},{"time":0.0333,"x":0,"y":0.5},{"time":0.0667,"x":0.63,"y":0.5},{"time":0.1,"x":0.63,"y":-0.25},{"time":0.1333,"x":0.25,"y":-0.25},{"time":0.1667,"x":0.25,"y":0.38},{"time":0.2,"x":1,"y":0.38},{"time":0.2333,"x":1,"y":0},{"time":0.2667,"x":0.5,"y":0},{"time":0.3,"x":0.5,"y":0.63},{"time":0.3333,"x":1.13,"y":0.63},{"time":0.3667,"x":1.13,"y":0.13},{"time":0.4,"x":0.75,"y":0.13},{"time":0.4333,"x":0.5,"y":0.38},{"time":0.4667,"x":0.5,"y":-0.25},{"time":0.5,"x":-0.12,"y":-0.25},{"time":0.5333,"x":-0.12,"y":0.38},{"time":0.5667,"x":0.63,"y":0.38},{"time":0.6,"x":0.63,"y":0},{"time":0.6333,"x":1,"y":0,"curve":"stepped"},{"time":0.6667,"x":1,"y":0},{"time":0.7,"x":0.63,"y":0.75},{"time":0.7333,"x":0.63,"y":0.38},{"time":0.7667,"x":0,"y":0},{"time":0.8,"x":1,"y":0},{"time":0.8333,"x":0.63,"y":0.75},{"time":0.8667,"x":0.63,"y":0.38},{"time":0.9,"x":0,"y":0},{"time":0.9333,"x":0.63,"y":0.38},{"time":0.9667,"x":0,"y":0}]},"che":{"translate":[{"time":0,"x":0,"y":0},{"time":0.4,"x":0,"y":0.36},{"time":0.4333,"x":-0.26,"y":0.36},{"time":0.4667,"x":-0.26,"y":0.1},{"time":0.5,"x":-0.26,"y":0.36},{"time":0.5333,"x":0.02,"y":0.36},{"time":0.5667,"x":-0.16,"y":0.36},{"time":0.6,"x":-0.16,"y":0.18},{"time":0.6333,"x":0.02,"y":0.18},{"time":0.6667,"x":-0.16,"y":0.18},{"time":0.7,"x":-0.16,"y":0.42},{"time":0.7333,"x":0.04,"y":0.42},{"time":0.7667,"x":-0.1,"y":0.42}]},"che2":{"translate":[{"time":0,"x":0,"y":0},{"time":0.4,"x":-3.09,"y":-1.33},{"time":0.9667,"x":0,"y":0}]}},"drawOrder":[{"time":0},{"time":0.9667}]}}}